vizelec/__init__.py
vizelec/main.py
vizelec/pinout.py
vizelec/spice.py
vizelec-0.1.2.dist-info/entry_points.txt
vizelec-0.1.2.dist-info/METADATA
vizelec-0.1.2.dist-info/WHEEL
vizelec-0.1.2.dist-info/RECORD
