Metadata-Version: 2.1
Name: vizelec
Version: 0.1.2
Summary: Generate drawing and graph of schematic from various files.
License: MIT
Author: Patarimi
Author-email: 38954040+Patarimi@users.noreply.github.com
Requires-Python: >=3.9,<4.0
Classifier: License :: OSI Approved :: MIT License
Classifier: Programming Language :: Python :: 3
Classifier: Programming Language :: Python :: 3.9
Classifier: Programming Language :: Python :: 3.10
Classifier: Programming Language :: Python :: 3.11
Requires-Dist: matplotlib (>=3.7.1,<4.0.0)
Requires-Dist: networkx (>=3.0,<4.0)
Requires-Dist: schemdraw (>=0.16,<0.17)
Requires-Dist: typer (>=0.7.0,<0.8.0)
